Metadata-Version: 1.1
Name: doudizhu-resolver
Version: 0.1.2
Summary: doudizhu puzzle resolver
Home-page: https://github.com/aohajin/doudizhu_resolver
Author: aohajin
Author-email: maohaijian@xiimoon.com
License: MIT License
